{
    "Ar36": {
        "error": 0.0002368230150468417,
        "error_type": "",
        "fit": "previous",
        "references": [
            {
                "exclude": false,
                "record_id": "ba-01-A-33035"
            }
        ],
        "value": 0.009055499638020948
    },
    "Ar37": {
        "error": 0.009990777768612217,
        "error_type": "",
        "fit": "previous",
        "references": [
            {
                "exclude": false,
                "record_id": "ba-01-A-33035"
            }
        ],
        "value": 0.011845238176495108
    },
    "Ar38": {
        "error": 0.010314535478290771,
        "error_type": "",
        "fit": "previous",
        "references": [
            {
                "exclude": false,
                "record_id": "ba-01-A-33035"
            }
        ],
        "value": 0.0032522202845226686
    },
    "Ar39": {
        "error": 0.00894243320085196,
        "error_type": "",
        "fit": "previous",
        "references": [
            {
                "exclude": false,
                "record_id": "ba-01-A-33035"
            }
        ],
        "value": 0.003824583922045941
    },
    "Ar40": {
        "error": 0.023078937082904327,
        "error_type": "",
        "fit": "previous",
        "references": [
            {
                "exclude": false,
                "record_id": "ba-01-A-33035"
            }
        ],
        "value": 2.3893475999638154
    }
}