{
    "AX": {
        "error": 0.00442921647382936,
        "error_type": "SEM",
        "filter_outliers_dict": {
            "filter_outliers": true,
            "iterations": 1,
            "std_devs": 2
        },
        "fit": "Average",
        "value": 0.019821565391890412
    },
    "CDD": {
        "error": 4.563600791020112e-06,
        "error_type": "SEM",
        "filter_outliers_dict": {
            "filter_outliers": false,
            "iterations": 1,
            "std_devs": 2
        },
        "fit": "Average",
        "value": 7.094370876211302e-06
    },
    "H1": {
        "error": 0.01267775677270939,
        "error_type": "SEM",
        "filter_outliers_dict": {
            "filter_outliers": true,
            "iterations": 1,
            "std_devs": 2
        },
        "fit": "Average",
        "value": -0.035953874983322386
    },
    "L1": {
        "error": 0.006525577293962047,
        "error_type": "SEM",
        "filter_outliers_dict": {
            "filter_outliers": true,
            "iterations": 1,
            "std_devs": 2
        },
        "fit": "Average",
        "value": -0.015273174890949372
    },
    "L2": {
        "error": 0.00577186550555794,
        "error_type": "SEM",
        "filter_outliers_dict": {
            "filter_outliers": false,
            "iterations": 1,
            "std_devs": 2
        },
        "fit": "Average",
        "value": -0.0057359937452176974
    }
}