{
    "Ar36": {
        "error": 0.00013445034286217595,
        "error_type": "",
        "fit": "previous",
        "references": [
            {
                "exclude": false,
                "record_id": "ba-01-A-17970"
            }
        ],
        "value": 0.003934053295198536
    },
    "Ar37": {
        "error": 0.00983352186186988,
        "error_type": "",
        "fit": "previous",
        "references": [
            {
                "exclude": false,
                "record_id": "ba-01-A-17970"
            }
        ],
        "value": -0.030358559277890294
    },
    "Ar38": {
        "error": 0.009752974698978406,
        "error_type": "",
        "fit": "previous",
        "references": [
            {
                "exclude": false,
                "record_id": "ba-01-A-17970"
            }
        ],
        "value": -0.011104686723451128
    },
    "Ar39": {
        "error": 0.008977583166749742,
        "error_type": "",
        "fit": "previous",
        "references": [
            {
                "exclude": false,
                "record_id": "ba-01-A-17970"
            }
        ],
        "value": 0.028670681673235884
    },
    "Ar40": {
        "error": 0.023111428405667864,
        "error_type": "",
        "fit": "previous",
        "references": [
            {
                "exclude": false,
                "record_id": "ba-01-A-17970"
            }
        ],
        "value": 1.003611573282344
    }
}