{
    "Ar36": {
        "error": 0.00015378738046428205,
        "error_type": "",
        "fit": "previous",
        "references": [
            {
                "exclude": false,
                "record_id": "ba-01-A-24932"
            }
        ],
        "value": 0.004949710385229952
    },
    "Ar37": {
        "error": 0.008787250077706168,
        "error_type": "",
        "fit": "previous",
        "references": [
            {
                "exclude": false,
                "record_id": "ba-01-A-24932"
            }
        ],
        "value": 0.039183657265692534
    },
    "Ar38": {
        "error": 0.01067874636262446,
        "error_type": "",
        "fit": "previous",
        "references": [
            {
                "exclude": false,
                "record_id": "ba-01-A-24932"
            }
        ],
        "value": 0.008487651345311799
    },
    "Ar39": {
        "error": 0.007775614752019209,
        "error_type": "",
        "fit": "previous",
        "references": [
            {
                "exclude": false,
                "record_id": "ba-01-A-24932"
            }
        ],
        "value": 0.02178243973917391
    },
    "Ar40": {
        "error": 0.024002818574620013,
        "error_type": "",
        "fit": "previous",
        "references": [
            {
                "exclude": false,
                "record_id": "ba-01-A-24932"
            }
        ],
        "value": 0.7954687884103233
    }
}